[ {
  "name" : "com.azure.resourcemanager.keyvault.generated.models.ErrorException",
  "allDeclaredConstructors" : true,
  "allDeclaredFields" : true,
  "allDeclaredMethods" : true
}, {
  "name" : "com.azure.resourcemanager.keyvault.generated.models.KeyCreateParameters",
  "allDeclaredConstructors" : true,
  "allDeclaredFields" : true,
  "allDeclaredMethods" : true
}, {
  "name" : "com.azure.resourcemanager.keyvault.generated.fluent.models.KeyProperties",
  "allDeclaredConstructors" : true,
  "allDeclaredFields" : true,
  "allDeclaredMethods" : true
}, {
  "name" : "com.azure.resourcemanager.keyvault.generated.models.KeyAttributes",
  "allDeclaredConstructors" : true,
  "allDeclaredFields" : true,
  "allDeclaredMethods" : true
}, {
  "name" : "com.azure.resourcemanager.keyvault.generated.models.RotationPolicy",
  "allDeclaredConstructors" : true,
  "allDeclaredFields" : true,
  "allDeclaredMethods" : true
}, {
  "name" : "com.azure.resourcemanager.keyvault.generated.models.KeyRotationPolicyAttributes",
  "allDeclaredConstructors" : true,
  "allDeclaredFields" : true,
  "allDeclaredMethods" : true
}, {
  "name" : "com.azure.resourcemanager.keyvault.generated.models.LifetimeAction",
  "allDeclaredConstructors" : true,
  "allDeclaredFields" : true,
  "allDeclaredMethods" : true
}, {
  "name" : "com.azure.resourcemanager.keyvault.generated.models.Trigger",
  "allDeclaredConstructors" : true,
  "allDeclaredFields" : true,
  "allDeclaredMethods" : true
}, {
  "name" : "com.azure.resourcemanager.keyvault.generated.models.Action",
  "allDeclaredConstructors" : true,
  "allDeclaredFields" : true,
  "allDeclaredMethods" : true
}, {
  "name" : "com.azure.resourcemanager.keyvault.generated.models.KeyReleasePolicy",
  "allDeclaredConstructors" : true,
  "allDeclaredFields" : true,
  "allDeclaredMethods" : true
}, {
  "name" : "com.azure.resourcemanager.keyvault.generated.fluent.models.KeyInner",
  "allDeclaredConstructors" : true,
  "allDeclaredFields" : true,
  "allDeclaredMethods" : true
}, {
  "name" : "com.azure.resourcemanager.keyvault.generated.models.KeyListResult",
  "allDeclaredConstructors" : true,
  "allDeclaredFields" : true,
  "allDeclaredMethods" : true
}, {
  "name" : "com.azure.resourcemanager.keyvault.generated.models.ManagedHsmKeyCreateParameters",
  "allDeclaredConstructors" : true,
  "allDeclaredFields" : true,
  "allDeclaredMethods" : true
}, {
  "name" : "com.azure.resourcemanager.keyvault.generated.fluent.models.ManagedHsmKeyProperties",
  "allDeclaredConstructors" : true,
  "allDeclaredFields" : true,
  "allDeclaredMethods" : true
}, {
  "name" : "com.azure.resourcemanager.keyvault.generated.models.ManagedHsmKeyAttributes",
  "allDeclaredConstructors" : true,
  "allDeclaredFields" : true,
  "allDeclaredMethods" : true
}, {
  "name" : "com.azure.resourcemanager.keyvault.generated.models.ManagedHsmRotationPolicy",
  "allDeclaredConstructors" : true,
  "allDeclaredFields" : true,
  "allDeclaredMethods" : true
}, {
  "name" : "com.azure.resourcemanager.keyvault.generated.models.ManagedHsmKeyRotationPolicyAttributes",
  "allDeclaredConstructors" : true,
  "allDeclaredFields" : true,
  "allDeclaredMethods" : true
}, {
  "name" : "com.azure.resourcemanager.keyvault.generated.models.ManagedHsmLifetimeAction",
  "allDeclaredConstructors" : true,
  "allDeclaredFields" : true,
  "allDeclaredMethods" : true
}, {
  "name" : "com.azure.resourcemanager.keyvault.generated.models.ManagedHsmTrigger",
  "allDeclaredConstructors" : true,
  "allDeclaredFields" : true,
  "allDeclaredMethods" : true
}, {
  "name" : "com.azure.resourcemanager.keyvault.generated.models.ManagedHsmAction",
  "allDeclaredConstructors" : true,
  "allDeclaredFields" : true,
  "allDeclaredMethods" : true
}, {
  "name" : "com.azure.resourcemanager.keyvault.generated.models.ManagedHsmKeyReleasePolicy",
  "allDeclaredConstructors" : true,
  "allDeclaredFields" : true,
  "allDeclaredMethods" : true
}, {
  "name" : "com.azure.resourcemanager.keyvault.generated.fluent.models.ManagedHsmKeyInner",
  "allDeclaredConstructors" : true,
  "allDeclaredFields" : true,
  "allDeclaredMethods" : true
}, {
  "name" : "com.azure.resourcemanager.keyvault.generated.models.ProxyResourceWithoutSystemData",
  "allDeclaredConstructors" : true,
  "allDeclaredFields" : true,
  "allDeclaredMethods" : true
}, {
  "name" : "com.azure.resourcemanager.keyvault.generated.models.ManagedHsmKeyListResult",
  "allDeclaredConstructors" : true,
  "allDeclaredFields" : true,
  "allDeclaredMethods" : true
}, {
  "name" : "com.azure.resourcemanager.keyvault.generated.models.VaultCreateOrUpdateParameters",
  "allDeclaredConstructors" : true,
  "allDeclaredFields" : true,
  "allDeclaredMethods" : true
}, {
  "name" : "com.azure.resourcemanager.keyvault.generated.models.VaultProperties",
  "allDeclaredConstructors" : true,
  "allDeclaredFields" : true,
  "allDeclaredMethods" : true
}, {
  "name" : "com.azure.resourcemanager.keyvault.generated.models.Sku",
  "allDeclaredConstructors" : true,
  "allDeclaredFields" : true,
  "allDeclaredMethods" : true
}, {
  "name" : "com.azure.resourcemanager.keyvault.generated.models.AccessPolicyEntry",
  "allDeclaredConstructors" : true,
  "allDeclaredFields" : true,
  "allDeclaredMethods" : true
}, {
  "name" : "com.azure.resourcemanager.keyvault.generated.models.Permissions",
  "allDeclaredConstructors" : true,
  "allDeclaredFields" : true,
  "allDeclaredMethods" : true
}, {
  "name" : "com.azure.resourcemanager.keyvault.generated.models.NetworkRuleSet",
  "allDeclaredConstructors" : true,
  "allDeclaredFields" : true,
  "allDeclaredMethods" : true
}, {
  "name" : "com.azure.resourcemanager.keyvault.generated.models.IpRule",
  "allDeclaredConstructors" : true,
  "allDeclaredFields" : true,
  "allDeclaredMethods" : true
}, {
  "name" : "com.azure.resourcemanager.keyvault.generated.models.VirtualNetworkRule",
  "allDeclaredConstructors" : true,
  "allDeclaredFields" : true,
  "allDeclaredMethods" : true
}, {
  "name" : "com.azure.resourcemanager.keyvault.generated.models.PrivateEndpointConnectionItem",
  "allDeclaredConstructors" : true,
  "allDeclaredFields" : true,
  "allDeclaredMethods" : true
}, {
  "name" : "com.azure.resourcemanager.keyvault.generated.fluent.models.PrivateEndpointConnectionProperties",
  "allDeclaredConstructors" : true,
  "allDeclaredFields" : true,
  "allDeclaredMethods" : true
}, {
  "name" : "com.azure.resourcemanager.keyvault.generated.models.PrivateEndpoint",
  "allDeclaredConstructors" : true,
  "allDeclaredFields" : true,
  "allDeclaredMethods" : true
}, {
  "name" : "com.azure.resourcemanager.keyvault.generated.models.PrivateLinkServiceConnectionState",
  "allDeclaredConstructors" : true,
  "allDeclaredFields" : true,
  "allDeclaredMethods" : true
}, {
  "name" : "com.azure.resourcemanager.keyvault.generated.fluent.models.VaultInner",
  "allDeclaredConstructors" : true,
  "allDeclaredFields" : true,
  "allDeclaredMethods" : true
}, {
  "name" : "com.azure.resourcemanager.keyvault.generated.models.VaultPatchParameters",
  "allDeclaredConstructors" : true,
  "allDeclaredFields" : true,
  "allDeclaredMethods" : true
}, {
  "name" : "com.azure.resourcemanager.keyvault.generated.models.VaultPatchProperties",
  "allDeclaredConstructors" : true,
  "allDeclaredFields" : true,
  "allDeclaredMethods" : true
}, {
  "name" : "com.azure.resourcemanager.keyvault.generated.fluent.models.VaultAccessPolicyParametersInner",
  "allDeclaredConstructors" : true,
  "allDeclaredFields" : true,
  "allDeclaredMethods" : true
}, {
  "name" : "com.azure.resourcemanager.keyvault.generated.models.VaultAccessPolicyProperties",
  "allDeclaredConstructors" : true,
  "allDeclaredFields" : true,
  "allDeclaredMethods" : true
}, {
  "name" : "com.azure.resourcemanager.keyvault.generated.models.VaultListResult",
  "allDeclaredConstructors" : true,
  "allDeclaredFields" : true,
  "allDeclaredMethods" : true
}, {
  "name" : "com.azure.resourcemanager.keyvault.generated.models.DeletedVaultListResult",
  "allDeclaredConstructors" : true,
  "allDeclaredFields" : true,
  "allDeclaredMethods" : true
}, {
  "name" : "com.azure.resourcemanager.keyvault.generated.fluent.models.DeletedVaultInner",
  "allDeclaredConstructors" : true,
  "allDeclaredFields" : true,
  "allDeclaredMethods" : true
}, {
  "name" : "com.azure.resourcemanager.keyvault.generated.models.DeletedVaultProperties",
  "allDeclaredConstructors" : true,
  "allDeclaredFields" : true,
  "allDeclaredMethods" : true
}, {
  "name" : "com.azure.resourcemanager.keyvault.generated.models.ResourceListResult",
  "allDeclaredConstructors" : true,
  "allDeclaredFields" : true,
  "allDeclaredMethods" : true
}, {
  "name" : "com.azure.resourcemanager.keyvault.generated.models.VaultCheckNameAvailabilityParameters",
  "allDeclaredConstructors" : true,
  "allDeclaredFields" : true,
  "allDeclaredMethods" : true
}, {
  "name" : "com.azure.resourcemanager.keyvault.generated.fluent.models.CheckNameAvailabilityResultInner",
  "allDeclaredConstructors" : true,
  "allDeclaredFields" : true,
  "allDeclaredMethods" : true
}, {
  "name" : "com.azure.resourcemanager.keyvault.generated.fluent.models.PrivateEndpointConnectionInner",
  "allDeclaredConstructors" : true,
  "allDeclaredFields" : true,
  "allDeclaredMethods" : true
}, {
  "name" : "com.azure.resourcemanager.keyvault.generated.models.PrivateEndpointConnectionListResult",
  "allDeclaredConstructors" : true,
  "allDeclaredFields" : true,
  "allDeclaredMethods" : true
}, {
  "name" : "com.azure.resourcemanager.keyvault.generated.fluent.models.PrivateLinkResourceListResultInner",
  "allDeclaredConstructors" : true,
  "allDeclaredFields" : true,
  "allDeclaredMethods" : true
}, {
  "name" : "com.azure.resourcemanager.keyvault.generated.models.PrivateLinkResource",
  "allDeclaredConstructors" : true,
  "allDeclaredFields" : true,
  "allDeclaredMethods" : true
}, {
  "name" : "com.azure.resourcemanager.keyvault.generated.fluent.models.PrivateLinkResourceProperties",
  "allDeclaredConstructors" : true,
  "allDeclaredFields" : true,
  "allDeclaredMethods" : true
}, {
  "name" : "com.azure.resourcemanager.keyvault.generated.fluent.models.ManagedHsmInner",
  "allDeclaredConstructors" : true,
  "allDeclaredFields" : true,
  "allDeclaredMethods" : true
}, {
  "name" : "com.azure.resourcemanager.keyvault.generated.models.ManagedHsmProperties",
  "allDeclaredConstructors" : true,
  "allDeclaredFields" : true,
  "allDeclaredMethods" : true
}, {
  "name" : "com.azure.resourcemanager.keyvault.generated.models.MhsmNetworkRuleSet",
  "allDeclaredConstructors" : true,
  "allDeclaredFields" : true,
  "allDeclaredMethods" : true
}, {
  "name" : "com.azure.resourcemanager.keyvault.generated.models.MhsmipRule",
  "allDeclaredConstructors" : true,
  "allDeclaredFields" : true,
  "allDeclaredMethods" : true
}, {
  "name" : "com.azure.resourcemanager.keyvault.generated.models.MhsmVirtualNetworkRule",
  "allDeclaredConstructors" : true,
  "allDeclaredFields" : true,
  "allDeclaredMethods" : true
}, {
  "name" : "com.azure.resourcemanager.keyvault.generated.fluent.models.MhsmGeoReplicatedRegionInner",
  "allDeclaredConstructors" : true,
  "allDeclaredFields" : true,
  "allDeclaredMethods" : true
}, {
  "name" : "com.azure.resourcemanager.keyvault.generated.models.MhsmPrivateEndpointConnectionItem",
  "allDeclaredConstructors" : true,
  "allDeclaredFields" : true,
  "allDeclaredMethods" : true
}, {
  "name" : "com.azure.resourcemanager.keyvault.generated.fluent.models.MhsmPrivateEndpointConnectionProperties",
  "allDeclaredConstructors" : true,
  "allDeclaredFields" : true,
  "allDeclaredMethods" : true
}, {
  "name" : "com.azure.resourcemanager.keyvault.generated.models.MhsmPrivateEndpoint",
  "allDeclaredConstructors" : true,
  "allDeclaredFields" : true,
  "allDeclaredMethods" : true
}, {
  "name" : "com.azure.resourcemanager.keyvault.generated.models.MhsmPrivateLinkServiceConnectionState",
  "allDeclaredConstructors" : true,
  "allDeclaredFields" : true,
  "allDeclaredMethods" : true
}, {
  "name" : "com.azure.resourcemanager.keyvault.generated.models.ManagedHsmSecurityDomainProperties",
  "allDeclaredConstructors" : true,
  "allDeclaredFields" : true,
  "allDeclaredMethods" : true
}, {
  "name" : "com.azure.resourcemanager.keyvault.generated.models.ManagedHsmResource",
  "allDeclaredConstructors" : true,
  "allDeclaredFields" : true,
  "allDeclaredMethods" : true
}, {
  "name" : "com.azure.resourcemanager.keyvault.generated.models.ManagedHsmSku",
  "allDeclaredConstructors" : true,
  "allDeclaredFields" : true,
  "allDeclaredMethods" : true
}, {
  "name" : "com.azure.resourcemanager.keyvault.generated.models.ManagedServiceIdentity",
  "allDeclaredConstructors" : true,
  "allDeclaredFields" : true,
  "allDeclaredMethods" : true
}, {
  "name" : "com.azure.resourcemanager.keyvault.generated.models.UserAssignedIdentity",
  "allDeclaredConstructors" : true,
  "allDeclaredFields" : true,
  "allDeclaredMethods" : true
}, {
  "name" : "com.azure.resourcemanager.keyvault.generated.models.Error",
  "allDeclaredConstructors" : true,
  "allDeclaredFields" : true,
  "allDeclaredMethods" : true
}, {
  "name" : "com.azure.resourcemanager.keyvault.generated.models.ManagedHsmListResult",
  "allDeclaredConstructors" : true,
  "allDeclaredFields" : true,
  "allDeclaredMethods" : true
}, {
  "name" : "com.azure.resourcemanager.keyvault.generated.models.MhsmPrivateEndpointConnectionsListResult",
  "allDeclaredConstructors" : true,
  "allDeclaredFields" : true,
  "allDeclaredMethods" : true
}, {
  "name" : "com.azure.resourcemanager.keyvault.generated.fluent.models.MhsmPrivateEndpointConnectionInner",
  "allDeclaredConstructors" : true,
  "allDeclaredFields" : true,
  "allDeclaredMethods" : true
}, {
  "name" : "com.azure.resourcemanager.keyvault.generated.models.DeletedManagedHsmListResult",
  "allDeclaredConstructors" : true,
  "allDeclaredFields" : true,
  "allDeclaredMethods" : true
}, {
  "name" : "com.azure.resourcemanager.keyvault.generated.fluent.models.DeletedManagedHsmInner",
  "allDeclaredConstructors" : true,
  "allDeclaredFields" : true,
  "allDeclaredMethods" : true
}, {
  "name" : "com.azure.resourcemanager.keyvault.generated.models.DeletedManagedHsmProperties",
  "allDeclaredConstructors" : true,
  "allDeclaredFields" : true,
  "allDeclaredMethods" : true
}, {
  "name" : "com.azure.resourcemanager.keyvault.generated.fluent.models.MhsmPrivateLinkResourceListResultInner",
  "allDeclaredConstructors" : true,
  "allDeclaredFields" : true,
  "allDeclaredMethods" : true
}, {
  "name" : "com.azure.resourcemanager.keyvault.generated.models.MhsmPrivateLinkResource",
  "allDeclaredConstructors" : true,
  "allDeclaredFields" : true,
  "allDeclaredMethods" : true
}, {
  "name" : "com.azure.resourcemanager.keyvault.generated.fluent.models.MhsmPrivateLinkResourceProperties",
  "allDeclaredConstructors" : true,
  "allDeclaredFields" : true,
  "allDeclaredMethods" : true
}, {
  "name" : "com.azure.resourcemanager.keyvault.generated.models.MhsmRegionsListResult",
  "allDeclaredConstructors" : true,
  "allDeclaredFields" : true,
  "allDeclaredMethods" : true
}, {
  "name" : "com.azure.resourcemanager.keyvault.generated.models.CheckMhsmNameAvailabilityParameters",
  "allDeclaredConstructors" : true,
  "allDeclaredFields" : true,
  "allDeclaredMethods" : true
}, {
  "name" : "com.azure.resourcemanager.keyvault.generated.fluent.models.CheckMhsmNameAvailabilityResultInner",
  "allDeclaredConstructors" : true,
  "allDeclaredFields" : true,
  "allDeclaredMethods" : true
}, {
  "name" : "com.azure.resourcemanager.keyvault.generated.models.OperationListResult",
  "allDeclaredConstructors" : true,
  "allDeclaredFields" : true,
  "allDeclaredMethods" : true
}, {
  "name" : "com.azure.resourcemanager.keyvault.generated.fluent.models.OperationInner",
  "allDeclaredConstructors" : true,
  "allDeclaredFields" : true,
  "allDeclaredMethods" : true
}, {
  "name" : "com.azure.resourcemanager.keyvault.generated.models.OperationDisplay",
  "allDeclaredConstructors" : true,
  "allDeclaredFields" : true,
  "allDeclaredMethods" : true
}, {
  "name" : "com.azure.resourcemanager.keyvault.generated.fluent.models.OperationProperties",
  "allDeclaredConstructors" : true,
  "allDeclaredFields" : true,
  "allDeclaredMethods" : true
}, {
  "name" : "com.azure.resourcemanager.keyvault.generated.models.ServiceSpecification",
  "allDeclaredConstructors" : true,
  "allDeclaredFields" : true,
  "allDeclaredMethods" : true
}, {
  "name" : "com.azure.resourcemanager.keyvault.generated.models.LogSpecification",
  "allDeclaredConstructors" : true,
  "allDeclaredFields" : true,
  "allDeclaredMethods" : true
}, {
  "name" : "com.azure.resourcemanager.keyvault.generated.models.MetricSpecification",
  "allDeclaredConstructors" : true,
  "allDeclaredFields" : true,
  "allDeclaredMethods" : true
}, {
  "name" : "com.azure.resourcemanager.keyvault.generated.models.DimensionProperties",
  "allDeclaredConstructors" : true,
  "allDeclaredFields" : true,
  "allDeclaredMethods" : true
}, {
  "name" : "com.azure.resourcemanager.keyvault.generated.models.SecretCreateOrUpdateParameters",
  "allDeclaredConstructors" : true,
  "allDeclaredFields" : true,
  "allDeclaredMethods" : true
}, {
  "name" : "com.azure.resourcemanager.keyvault.generated.models.SecretProperties",
  "allDeclaredConstructors" : true,
  "allDeclaredFields" : true,
  "allDeclaredMethods" : true
}, {
  "name" : "com.azure.resourcemanager.keyvault.generated.models.SecretAttributes",
  "allDeclaredConstructors" : true,
  "allDeclaredFields" : true,
  "allDeclaredMethods" : true
}, {
  "name" : "com.azure.resourcemanager.keyvault.generated.models.Attributes",
  "allDeclaredConstructors" : true,
  "allDeclaredFields" : true,
  "allDeclaredMethods" : true
}, {
  "name" : "com.azure.resourcemanager.keyvault.generated.fluent.models.SecretInner",
  "allDeclaredConstructors" : true,
  "allDeclaredFields" : true,
  "allDeclaredMethods" : true
}, {
  "name" : "com.azure.resourcemanager.keyvault.generated.models.SecretPatchParameters",
  "allDeclaredConstructors" : true,
  "allDeclaredFields" : true,
  "allDeclaredMethods" : true
}, {
  "name" : "com.azure.resourcemanager.keyvault.generated.models.SecretPatchProperties",
  "allDeclaredConstructors" : true,
  "allDeclaredFields" : true,
  "allDeclaredMethods" : true
}, {
  "name" : "com.azure.resourcemanager.keyvault.generated.models.SecretListResult",
  "allDeclaredConstructors" : true,
  "allDeclaredFields" : true,
  "allDeclaredMethods" : true
}, {
  "name" : "com.azure.resourcemanager.keyvault.generated.models.PrivateEndpointConnectionsPutHeaders",
  "allDeclaredConstructors" : true,
  "allDeclaredFields" : true,
  "allDeclaredMethods" : true
}, {
  "name" : "com.azure.resourcemanager.keyvault.generated.models.MhsmPrivateEndpointConnectionsPutHeaders",
  "allDeclaredConstructors" : true,
  "allDeclaredFields" : true,
  "allDeclaredMethods" : true
}, {
  "name" : "com.azure.resourcemanager.keyvault.generated.models.DeletionRecoveryLevel",
  "allDeclaredConstructors" : true,
  "allDeclaredFields" : true,
  "allDeclaredMethods" : true
}, {
  "name" : "com.azure.resourcemanager.keyvault.generated.models.JsonWebKeyType",
  "allDeclaredConstructors" : true,
  "allDeclaredFields" : true,
  "allDeclaredMethods" : true
}, {
  "name" : "com.azure.resourcemanager.keyvault.generated.models.JsonWebKeyOperation",
  "allDeclaredConstructors" : true,
  "allDeclaredFields" : true,
  "allDeclaredMethods" : true
}, {
  "name" : "com.azure.resourcemanager.keyvault.generated.models.JsonWebKeyCurveName",
  "allDeclaredConstructors" : true,
  "allDeclaredFields" : true,
  "allDeclaredMethods" : true
}, {
  "name" : "com.azure.resourcemanager.keyvault.generated.models.SkuFamily",
  "allDeclaredConstructors" : true,
  "allDeclaredFields" : true,
  "allDeclaredMethods" : true
}, {
  "name" : "com.azure.resourcemanager.keyvault.generated.models.KeyPermissions",
  "allDeclaredConstructors" : true,
  "allDeclaredFields" : true,
  "allDeclaredMethods" : true
}, {
  "name" : "com.azure.resourcemanager.keyvault.generated.models.SecretPermissions",
  "allDeclaredConstructors" : true,
  "allDeclaredFields" : true,
  "allDeclaredMethods" : true
}, {
  "name" : "com.azure.resourcemanager.keyvault.generated.models.CertificatePermissions",
  "allDeclaredConstructors" : true,
  "allDeclaredFields" : true,
  "allDeclaredMethods" : true
}, {
  "name" : "com.azure.resourcemanager.keyvault.generated.models.StoragePermissions",
  "allDeclaredConstructors" : true,
  "allDeclaredFields" : true,
  "allDeclaredMethods" : true
}, {
  "name" : "com.azure.resourcemanager.keyvault.generated.models.NetworkRuleBypassOptions",
  "allDeclaredConstructors" : true,
  "allDeclaredFields" : true,
  "allDeclaredMethods" : true
}, {
  "name" : "com.azure.resourcemanager.keyvault.generated.models.NetworkRuleAction",
  "allDeclaredConstructors" : true,
  "allDeclaredFields" : true,
  "allDeclaredMethods" : true
}, {
  "name" : "com.azure.resourcemanager.keyvault.generated.models.VaultProvisioningState",
  "allDeclaredConstructors" : true,
  "allDeclaredFields" : true,
  "allDeclaredMethods" : true
}, {
  "name" : "com.azure.resourcemanager.keyvault.generated.models.PrivateEndpointServiceConnectionStatus",
  "allDeclaredConstructors" : true,
  "allDeclaredFields" : true,
  "allDeclaredMethods" : true
}, {
  "name" : "com.azure.resourcemanager.keyvault.generated.models.ActionsRequired",
  "allDeclaredConstructors" : true,
  "allDeclaredFields" : true,
  "allDeclaredMethods" : true
}, {
  "name" : "com.azure.resourcemanager.keyvault.generated.models.PrivateEndpointConnectionProvisioningState",
  "allDeclaredConstructors" : true,
  "allDeclaredFields" : true,
  "allDeclaredMethods" : true
}, {
  "name" : "com.azure.resourcemanager.keyvault.generated.models.ProvisioningState",
  "allDeclaredConstructors" : true,
  "allDeclaredFields" : true,
  "allDeclaredMethods" : true
}, {
  "name" : "com.azure.resourcemanager.keyvault.generated.models.GeoReplicationRegionProvisioningState",
  "allDeclaredConstructors" : true,
  "allDeclaredFields" : true,
  "allDeclaredMethods" : true
}, {
  "name" : "com.azure.resourcemanager.keyvault.generated.models.PublicNetworkAccess",
  "allDeclaredConstructors" : true,
  "allDeclaredFields" : true,
  "allDeclaredMethods" : true
}, {
  "name" : "com.azure.resourcemanager.keyvault.generated.models.ActivationStatus",
  "allDeclaredConstructors" : true,
  "allDeclaredFields" : true,
  "allDeclaredMethods" : true
}, {
  "name" : "com.azure.resourcemanager.keyvault.generated.models.ManagedHsmSkuFamily",
  "allDeclaredConstructors" : true,
  "allDeclaredFields" : true,
  "allDeclaredMethods" : true
}, {
  "name" : "com.azure.resourcemanager.keyvault.generated.models.ManagedServiceIdentityType",
  "allDeclaredConstructors" : true,
  "allDeclaredFields" : true,
  "allDeclaredMethods" : true
}, {
  "name" : "com.azure.resourcemanager.keyvault.generated.models.KeyRotationPolicyActionType",
  "allDeclaredConstructors" : true,
  "allDeclaredFields" : true,
  "allDeclaredMethods" : true
}, {
  "name" : "com.azure.resourcemanager.keyvault.generated.models.SkuName",
  "allDeclaredConstructors" : true,
  "allDeclaredFields" : true,
  "allDeclaredMethods" : true
}, {
  "name" : "com.azure.resourcemanager.keyvault.generated.models.CreateMode",
  "allDeclaredConstructors" : true,
  "allDeclaredFields" : true,
  "allDeclaredMethods" : true
}, {
  "name" : "com.azure.resourcemanager.keyvault.generated.models.AccessPolicyUpdateKind",
  "allDeclaredConstructors" : true,
  "allDeclaredFields" : true,
  "allDeclaredMethods" : true
}, {
  "name" : "com.azure.resourcemanager.keyvault.generated.models.Reason",
  "allDeclaredConstructors" : true,
  "allDeclaredFields" : true,
  "allDeclaredMethods" : true
}, {
  "name" : "com.azure.resourcemanager.keyvault.generated.models.ManagedHsmSkuName",
  "allDeclaredConstructors" : true,
  "allDeclaredFields" : true,
  "allDeclaredMethods" : true
} ]